express/__init__.py
express/check_express.py
check_express-0.0.1.dist-info/METADATA
check_express-0.0.1.dist-info/WHEEL
check_express-0.0.1.dist-info/top_level.txt
check_express-0.0.1.dist-info/RECORD
