Metadata-Version: 2.1
Name: check-express
Version: 0.0.1
Summary: check express by express_id
Home-page: http://106.12.107.253/
Author: sunqiang
Author-email: 530631372@qq.com
License: UNKNOWN
Platform: UNKNOWN
Classifier: Programming Language :: Python :: 3
Classifier: License :: OSI Approved :: MIT License
Classifier: Operating System :: OS Independent
